kartoffel/__init__.py
kartoffel/kartoffel.py
kartoffel/launcher.py
kartoffel-0.1.dist-info/entry_points.txt
kartoffel-0.1.dist-info/LICENSE
kartoffel-0.1.dist-info/WHEEL
kartoffel-0.1.dist-info/METADATA
kartoffel-0.1.dist-info/RECORD
