Metadata-Version: 1.2
Name: kartoffel
Version: 0.1
Summary: Identify modules used in a Python application by running it.
Home-page: https://gitlab.com/takluyver/kartoffel
License: UNKNOWN
Author: Thomas Kluyver
Author-email: thomas@kluyver.me.uk
Requires-Python: >=3.5
Classifier: License :: OSI Approved :: MIT License
Requires-Dist: stdlib-list
